LICENSE
redis_data_transfer/__init__.py
redis_data_transfer/display.py
redis_data_transfer/processing.py
redis_data_transfer/redis_client.py
redis_data_transfer/state.py
redis_data_transfer-1.1.0.dist-info/entry_points.txt
redis_data_transfer-1.1.0.dist-info/LICENSE
redis_data_transfer-1.1.0.dist-info/WHEEL
redis_data_transfer-1.1.0.dist-info/METADATA
redis_data_transfer-1.1.0.dist-info/RECORD
