Metadata-Version: 2.1
Name: redis-data-transfer
Version: 1.1.0
Summary: Transfer data between a redis instances or clusters
Home-page: https://github.com/EDITD/redis_data_transfer
License: MIT
Author: EDITED Devs
Author-email: dev@edited.com
Requires-Python: >=3.6,<4.0
Classifier: Development Status :: 5 - Production/Stable
Classifier: Environment :: Console
Classifier: Intended Audience :: System Administrators
Classifier: License :: OSI Approved :: MIT License
Classifier: Programming Language :: Python :: 3
Classifier: Programming Language :: Python :: 3.10
Classifier: Programming Language :: Python :: 3.6
Classifier: Programming Language :: Python :: 3.7
Classifier: Programming Language :: Python :: 3.8
Classifier: Programming Language :: Python :: 3.9
Classifier: Topic :: Database
Classifier: Topic :: System :: Systems Administration
Classifier: Topic :: Utilities
Requires-Dist: redis-py-cluster (>=2.0.0,<2.1.0)
Requires-Dist: setproctitle (>=1.1.10,<1.2.0)
Project-URL: Repository, https://github.com/EDITD/redis_data_transfer
